{
    "directory_name": "infer_2023_12_02_01_42_59",
    "config": {
        "dataset": "FB15k-237",
        "model": "TransE",
        "output_dir": "/data/d1/kgem/results",
        "epochs": 1000,
        "cpu_monitor_interval": 0.5,
        "seed": 468,
        "timestamp": "2023_12_02_01_42_59",
        "train_logdir": "/data/d1/kgem/results/train_2023_12_02_01_41_11"
    },
    "emissions": {
        "timestamp": {
            "0": "2023-12-02T01:43:00"
        },
        "project_name": {
            "0": "codecarbon"
        },
        "run_id": {
            "0": "19349ccf-dbbb-4fe0-b07e-021edef6fb30"
        },
        "duration": {
            "0": 0.0054709911346435
        },
        "emissions": {
            "0": 2.9846676754725975e-08
        },
        "emissions_rate": {
            "0": 5.4554423540791455e-06
        },
        "cpu_power": {
            "0": 34.06945655367838
        },
        "gpu_power": {
            "0": 0.0
        },
        "ram_power": {
            "0": 23.42510032653809
        },
        "cpu_energy": {
            "0": 5.016726235644586e-08
        },
        "gpu_energy": {
            "0": 0.0
        },
        "ram_energy": {
            "0": 3.149773093923613e-08
        },
        "energy_consumed": {
            "0": 8.1664993295682e-08
        },
        "country_name": {
            "0": "Germany"
        },
        "country_iso_code": {
            "0": "DEU"
        },
        "region": {
            "0": NaN
        },
        "cloud_provider": {
            "0": NaN
        },
        "cloud_region": {
            "0": NaN
        },
        "os": {
            "0": "Linux-5.15.0-88-generic-x86_64-with-glibc2.35"
        },
        "python_version": {
            "0": "3.10.12"
        },
        "codecarbon_version": {
            "0": "2.3.1"
        },
        "cpu_count": {
            "0": 32
        },
        "cpu_model": {
            "0": "13th Gen Intel(R) Core(TM) i9-13900K"
        },
        "gpu_count": {
            "0": 1
        },
        "gpu_model": {
            "0": "1 x NVIDIA GeForce RTX 4090"
        },
        "longitude": {
            "0": NaN
        },
        "latitude": {
            "0": NaN
        },
        "ram_total_size": {
            "0": 62.46693420410156
        },
        "tracking_mode": {
            "0": "machine"
        },
        "on_cloud": {
            "0": "N"
        },
        "pue": {
            "0": 1.0
        }
    },
    "execution_platform": {
        "System": "Linux",
        "Node Name": "lamws027",
        "Release": "5.15.0-88-generic",
        "Version": "#98-Ubuntu SMP Mon Oct 2 15:18:56 UTC 2023",
        "Machine": "x86_64",
        "Processor": "13th Gen Intel(R) Core(TM) i9-13900K",
        "Physical cores": 24,
        "Total cores": 32,
        "Max Frequency": 4937.5,
        "Min Frequency": 800.0,
        "Current Frequency": 3075.080875,
        "Total": 67073359872,
        "Available": 62050230272,
        "Used": 4240285696
    },
    "validation_results": {
        "metrics": {
            "Hits@1": 0.10962422937665134,
            "Hits@3": 0.1912124474018984,
            "Hits@5": 0.24055680594970152,
            "Hits@10": 0.3204080634112927,
            "Mean Reciprocal Rank": 0.17937494814395905
        },
        "start": 1701481380.48706,
        "end": 1701481380.4912198,
        "model": {
            "params": 737100,
            "fsize": 2948400
        }
    },
    "full_log": "results_kgem\\infer_2023_12_02_01_42_59.tar.gz"
}