{
    "directory_name": "train_2023_11_30_17_38_22",
    "config": {
        "dataset": "kinships",
        "model": "HolE",
        "output_dir": "/data/d1/kgem/results",
        "epochs": 1000,
        "cpu_monitor_interval": 0.5,
        "seed": 135,
        "timestamp": "2023_11_30_17_38_22"
    },
    "emissions": {
        "timestamp": {
            "0": "2023-11-30T17:38:31"
        },
        "project_name": {
            "0": "codecarbon"
        },
        "run_id": {
            "0": "95d948b3-9c64-40ba-9682-b8fdcabff83d"
        },
        "duration": {
            "0": 7.42484450340271
        },
        "emissions": {
            "0": 9.500754472393078e-05
        },
        "emissions_rate": {
            "0": 1.2795896894593556e-05
        },
        "cpu_power": {
            "0": 39.1079300952509
        },
        "gpu_power": {
            "0": 78.72885545019321
        },
        "ram_power": {
            "0": 23.42510032653809
        },
        "cpu_energy": {
            "0": 7.559792658940433e-05
        },
        "gpu_energy": {
            "0": 0.0001372384431252
        },
        "ram_energy": {
            "0": 4.711855145388199e-05
        },
        "energy_consumed": {
            "0": 0.0002599549211685
        },
        "country_name": {
            "0": "Germany"
        },
        "country_iso_code": {
            "0": "DEU"
        },
        "region": {
            "0": NaN
        },
        "cloud_provider": {
            "0": NaN
        },
        "cloud_region": {
            "0": NaN
        },
        "os": {
            "0": "Linux-5.15.0-88-generic-x86_64-with-glibc2.35"
        },
        "python_version": {
            "0": "3.10.12"
        },
        "codecarbon_version": {
            "0": "2.3.1"
        },
        "cpu_count": {
            "0": 32
        },
        "cpu_model": {
            "0": "13th Gen Intel(R) Core(TM) i9-13900K"
        },
        "gpu_count": {
            "0": 1
        },
        "gpu_model": {
            "0": "1 x NVIDIA GeForce RTX 4090"
        },
        "longitude": {
            "0": NaN
        },
        "latitude": {
            "0": NaN
        },
        "ram_total_size": {
            "0": 62.46693420410156
        },
        "tracking_mode": {
            "0": "machine"
        },
        "on_cloud": {
            "0": "N"
        },
        "pue": {
            "0": 1.0
        }
    },
    "execution_platform": {
        "System": "Linux",
        "Node Name": "lamws027",
        "Release": "5.15.0-88-generic",
        "Version": "#98-Ubuntu SMP Mon Oct 2 15:18:56 UTC 2023",
        "Machine": "x86_64",
        "Processor": "13th Gen Intel(R) Core(TM) i9-13900K",
        "Physical cores": 24,
        "Total cores": 32,
        "Max Frequency": 4937.5,
        "Min Frequency": 800.0,
        "Current Frequency": 3060.158875,
        "Total": 67073359872,
        "Available": 63013744640,
        "Used": 3295555584
    },
    "results": {
        "history": {
            "loss": [
                0.9992344887817607,
                0.9821286955300499,
                0.9645049168783075,
                0.9342757814070758,
                0.8889796576079201,
                0.7568295072106754,
                0.4036714802770054,
                0.25481055326321544,
                0.23953263856032314,
                0.2267632782459259,
                0.21677356651600668,
                0.22291424344567692,
                0.20872432826196446,
                0.19667762780890746,
                0.19523539043524685,
                0.18992613124496796,
                0.1802846776211963,
                0.18430673287195318,
                0.16932672590893857,
                0.16600699722766876,
                0.15879134373629794,
                0.16461495353895075,
                0.15729466694242814,
                0.16156991768409223,
                0.15200171531999812,
                0.15397720455246813,
                0.15524739377638874,
                0.14685864724657116,
                0.15602081466247053,
                0.1431726876865415,
                0.1476851885809618,
                0.142112467876252,
                0.14049991614678325,
                0.14439916084794438,
                0.13763858816202948,
                0.1413315098513575,
                0.13932659827611027,
                0.13571852577083252,
                0.13738999143242836,
                0.13328015300280907,
                0.1321024789529688,
                0.13835537170662598,
                0.13895278424024582,
                0.12834047679515445,
                0.14037772903547568,
                0.1308169391225366,
                0.12428785948192372,
                0.12644045449355068,
                0.1354924852357191,
                0.1278148319791345,
                0.1336672735564849,
                0.11934713953558136,
                0.1259068165193586,
                0.12946775906226216,
                0.13075471318819942,
                0.12525908013477044,
                0.119164730038713,
                0.12611624971032143,
                0.12324030193335869,
                0.12446820648277507,
                0.11878749969251015,
                0.1207217828315847,
                0.12576039990081506,
                0.11975055428988793,
                0.12543929784613497,
                0.11676092664985095,
                0.11979152525172514,
                0.12175176752840772,
                0.12058165231171776,
                0.11502739589880495,
                0.12121030447237632,
                0.12357431825469523,
                0.11615142182392232,
                0.12163126052302473,
                0.12016086061211194,
                0.11766226151410271,
                0.11303402483463287,
                0.11527479702935499,
                0.10976245539153323,
                0.11994328021126635
            ]
        },
        "start": 1701365904.0442872,
        "end": 1701365911.4678833,
        "model": null
    },
    "full_log": "results_kgem\\train_2023_11_30_17_38_22.tar.gz"
}