{
    "directory_name": "train_2023_12_02_20_20_32",
    "config": {
        "dataset": "WN18-RR",
        "model": "SimplE",
        "output_dir": "/data/d1/kgem/results",
        "epochs": 1000,
        "cpu_monitor_interval": 0.5,
        "seed": 42,
        "timestamp": "2023_12_02_20_20_32"
    },
    "emissions": {
        "timestamp": {
            "0": "2023-12-02T20:28:27"
        },
        "project_name": {
            "0": "codecarbon"
        },
        "run_id": {
            "0": "fce15dbd-f5cf-4ffd-b5ad-8e36c041d566"
        },
        "duration": {
            "0": 473.2153027057648
        },
        "emissions": {
            "0": 0.01139615684374
        },
        "emissions_rate": {
            "0": 2.408239289511308e-05
        },
        "cpu_power": {
            "0": 38.8349259278129
        },
        "gpu_power": {
            "0": 220.72796351103528
        },
        "ram_power": {
            "0": 23.42510032653809
        },
        "cpu_energy": {
            "0": 0.0049648783974551
        },
        "gpu_energy": {
            "0": 0.0231653826989592
        },
        "ram_energy": {
            "0": 0.0030513367708661
        },
        "energy_consumed": {
            "0": 0.0311815978672805
        },
        "country_name": {
            "0": "Germany"
        },
        "country_iso_code": {
            "0": "DEU"
        },
        "region": {
            "0": NaN
        },
        "cloud_provider": {
            "0": NaN
        },
        "cloud_region": {
            "0": NaN
        },
        "os": {
            "0": "Linux-5.15.0-88-generic-x86_64-with-glibc2.35"
        },
        "python_version": {
            "0": "3.10.12"
        },
        "codecarbon_version": {
            "0": "2.3.1"
        },
        "cpu_count": {
            "0": 32
        },
        "cpu_model": {
            "0": "13th Gen Intel(R) Core(TM) i9-13900K"
        },
        "gpu_count": {
            "0": 1
        },
        "gpu_model": {
            "0": "1 x NVIDIA GeForce RTX 4090"
        },
        "longitude": {
            "0": NaN
        },
        "latitude": {
            "0": NaN
        },
        "ram_total_size": {
            "0": 62.46693420410156
        },
        "tracking_mode": {
            "0": "machine"
        },
        "on_cloud": {
            "0": "N"
        },
        "pue": {
            "0": 1.0
        }
    },
    "execution_platform": {
        "System": "Linux",
        "Node Name": "lamws027",
        "Release": "5.15.0-88-generic",
        "Version": "#98-Ubuntu SMP Mon Oct 2 15:18:56 UTC 2023",
        "Machine": "x86_64",
        "Processor": "13th Gen Intel(R) Core(TM) i9-13900K",
        "Physical cores": 24,
        "Total cores": 32,
        "Max Frequency": 4937.5,
        "Min Frequency": 800.0,
        "Current Frequency": 3039.91634375,
        "Total": 67073359872,
        "Available": 62481309696,
        "Used": 3828088832
    },
    "results": {
        "history": {
            "loss": [
                5.9928346900378955,
                4.894655409279991,
                3.9324358736767486,
                3.2070335563491374,
                2.6063059631515952,
                2.110371672405916,
                1.7355378210544585,
                1.433225305290783,
                1.2045006441719392,
                1.0069532120929046,
                0.8477962521945729,
                0.7281044186038129,
                0.6192862184170415,
                0.5368051464066786,
                0.47209301178946217,
                0.4085077940541155,
                0.3662849077845321,
                0.3216806772877188,
                0.2870073672822293,
                0.2550431204631048,
                0.2279843502842328,
                0.20867537422215238,
                0.19308724862468593,
                0.17755969079101788,
                0.1592092781601583,
                0.1459269223844304,
                0.13444613964461227,
                0.12320051040938672,
                0.11562246555900749,
                0.10847929610377725,
                0.09976267331718083,
                0.09322776204413351,
                0.08535507271778496,
                0.07865965423338553,
                0.07676203037502573,
                0.07065872179672998,
                0.06717852333779721,
                0.06058119909498868,
                0.05683570817551192,
                0.05674928416607573,
                0.05278688846156001,
                0.05268642549019526,
                0.048186084033702226,
                0.04705719947541023,
                0.044137170724570754,
                0.040859623310868357,
                0.04095713080126135,
                0.04165265964179793,
                0.03901045632767765,
                0.03354542400304447,
                0.034998528390903685,
                0.03372914473635747,
                0.03040153802756001,
                0.03110711408833809,
                0.028512246854712858,
                0.02733686421997845,
                0.027447743254357622,
                0.026335937244927183,
                0.025161491687793067,
                0.02267052392639658,
                0.02290145666612422,
                0.022252291380701696,
                0.02400534384719589,
                0.023066824701998164,
                0.021795404984560958,
                0.020118489173953147,
                0.0206639642279376,
                0.021102136828224448,
                0.018475477734361503,
                0.01951276983189232,
                0.017619450762867927,
                0.018862984165111008,
                0.01764485180268393,
                0.0159538833248114,
                0.017006388873628833,
                0.016757219832609683,
                0.015825472807730823,
                0.015295334130196887,
                0.015536756862831467,
                0.013963766013929511,
                0.014357301748960334,
                0.013509768751614235,
                0.014161333041813443,
                0.013737578605137328,
                0.013774467440431608,
                0.01435287743806839,
                0.012856192443081562,
                0.013942766786717317,
                0.013382053191718809,
                0.011377144763794015,
                0.011823576759985265,
                0.01254612137837445,
                0.011133153780418284,
                0.011518815904855728,
                0.011435636475353556,
                0.011690877449205692,
                0.01190990443505785,
                0.010252094262635665,
                0.010459930408636436,
                0.010525664090442553,
                0.010086044406189638,
                0.010197545401751995,
                0.009974972492850879,
                0.009697704485562795,
                0.00913244719233583,
                0.00997831155272091,
                0.009515472616562073,
                0.009514476224670516,
                0.009473931937314132,
                0.009744736447464675,
                0.00885848943144083,
                0.008700242586543455,
                0.008581560652922182,
                0.008796425245921401,
                0.008503893319079105,
                0.00833580536658273,
                0.008581987817716949,
                0.008799844980239868,
                0.007800015681149328,
                0.007749771345954608,
                0.008410140784347759,
                0.0071294253198977775,
                0.007275441294426427,
                0.007502040382036392,
                0.007496662120170453,
                0.007405360760715078,
                0.007525948911686154,
                0.0078005713465459205,
                0.008041264933040913,
                0.007613820199142484,
                0.006861747686258133,
                0.006770812254399061,
                0.007552492889740011,
                0.006224324625423726,
                0.006743322274483302,
                0.007140062141286976,
                0.005741940300418612,
                0.006109250194447882,
                0.006412657426998896,
                0.005561692327918376,
                0.006635208521038294,
                0.006325666129808215,
                0.006308466448065112,
                0.006234424227081678,
                0.006693357322365046,
                0.0063601951881804885,
                0.005607680308029932,
                0.005630843198912985,
                0.005402285255053464,
                0.0054541798911112195,
                0.006382765325115007,
                0.005915527100510457,
                0.005659624342532719,
                0.005684521509444013,
                0.005204510513473959,
                0.006066626748617958,
                0.005848660484394606,
                0.005038568306276027,
                0.005170982626869398,
                0.0062685508938396675,
                0.005090310490306686,
                0.0059904302360818664,
                0.005474360292667852,
                0.005260307577383869,
                0.005157681927084923,
                0.004783791709033882,
                0.004688348078771549,
                0.006029502948855653,
                0.00550849028479527,
                0.004559056575903121,
                0.00502583041020176,
                0.005486124069156015,
                0.005181681529125746,
                0.004617441440110698,
                0.004796224520267809,
                0.004294561140020104,
                0.004651002372231553,
                0.004664682109347161,
                0.004090279088739087,
                0.004586776975980577,
                0.00527921412140131,
                0.004582962744376239,
                0.004259350556222831,
                0.005178178063429454,
                0.004503262766143855,
                0.004887364322648329,
                0.004207765519180719,
                0.004674345452119323,
                0.0038152518517830794,
                0.0043678294346832175,
                0.004551764944677844,
                0.0033496852799811782,
                0.004344681234044187,
                0.0031583442407495835,
                0.0037646924255087095,
                0.004317598072264124,
                0.004692825099782032,
                0.003985118816661484,
                0.003852048587492284,
                0.004366013226921067,
                0.003983830592101988,
                0.004447781573981046,
                0.003940916335319771,
                0.004285359935944571,
                0.0035782393396777265,
                0.004228569331633694,
                0.0042538983583012046,
                0.003798562419765136,
                0.003283468962592237,
                0.004319721016594592,
                0.003824159349588787,
                0.0039418551468235604,
                0.0043499291984035685,
                0.003930875439854229,
                0.004019078135709552,
                0.004086238310179289,
                0.0034173706382074776,
                0.0036946311538272043,
                0.003187670394339982,
                0.0039176907992976556,
                0.003718501384205678,
                0.003266108638661749,
                0.0031802625176222885,
                0.003671514330541386,
                0.0036460950806298676,
                0.003217235382865457,
                0.003545121629448498,
                0.0032516693915514384,
                0.003990686879328945,
                0.003840776302796953,
                0.003626489798154901,
                0.00414447824963752,
                0.003900828875382157,
                0.0031220447381629665,
                0.003870088420808315,
                0.00291579693884534,
                0.003500420104383546,
                0.0033297972808427672,
                0.003810589656452922,
                0.003577541954377118,
                0.0033025810440235276,
                0.002837877978077706,
                0.0034581595429164524,
                0.003342627509332755,
                0.0037864634602823677,
                0.003480123816167607,
                0.0031171062522951294,
                0.0030137744513066378,
                0.003433618869851617,
                0.002797214823829777,
                0.00338845938882407,
                0.004086725895895677,
                0.0029107871629736,
                0.002812079301870921,
                0.0032596486017984505,
                0.002928689993260538,
                0.0030145112370305203,
                0.0037373291273765704,
                0.0025579451528542183,
                0.0028785802533521374,
                0.003522655975950115,
                0.0031376023995963965,
                0.002879452256157118,
                0.0026144638657569887,
                0.0026628541842322138,
                0.0038790990762850816,
                0.003268758174689377,
                0.003764540680191096,
                0.0028427646276267134,
                0.0028565933270489467,
                0.0027130252188619446,
                0.0033241517184411777,
                0.0035636216402053834,
                0.003890417258748237,
                0.0023821544997832352,
                0.0030773506390259545,
                0.002885151210734073,
                0.0030305923072292524,
                0.0026769438320223024,
                0.0031944775351268402,
                0.0031484541428439755,
                0.0027022942462388206,
                0.002831529310959227,
                0.003068717382848263,
                0.0025161347132833566,
                0.0022965311346685186,
                0.0026191322954700275,
                0.002957399485304075,
                0.003159733905511744,
                0.0034433031728600756,
                0.0031954335322713153,
                0.004217731459614109,
                0.0025279556729776017,
                0.0028459928162834222,
                0.0030774258844116155,
                0.00294976186226396,
                0.003086208102895933,
                0.002860450081746368,
                0.003251380807555774,
                0.0025234895977465544,
                0.0018264803542372059,
                0.0024579627494163373,
                0.0027545306995949326,
                0.002732882818535847,
                0.002388982825419482,
                0.0031855774385964168,
                0.0030549761729643625,
                0.002355381512247464,
                0.0030568367637255614,
                0.0027884844142724487,
                0.0027093373348607737,
                0.0032194070353665774,
                0.0027008861632031554,
                0.002918339055031538,
                0.0026593298870412744,
                0.003088914761867593,
                0.0026243930244270494,
                0.002676382995046237,
                0.002513441607794341,
                0.002961205844493473,
                0.0035194857484277557,
                0.0028790727860349067,
                0.0024935615084627095,
                0.0033193417167400614,
                0.0024325052550172106,
                0.0021121955367133897,
                0.0023468774743378162,
                0.0025532314992126296,
                0.0026400129584705128,
                0.0026551669408731602,
                0.0029639551416039468,
                0.0023738095043774913,
                0.002268294946235769,
                0.0020922451827894237,
                0.0025714257677250047,
                0.0028224692077321164,
                0.002350833124535925,
                0.0033552600947373053,
                0.0022931253647103028,
                0.0024134604369892795,
                0.002167524813729174,
                0.002508282579262467,
                0.0025740969542633087,
                0.0019879211726434092,
                0.002122195311548079,
                0.0028819222770193045,
                0.0030490541995009954,
                0.002429411741083159,
                0.0026900362880790934,
                0.0019297687336802482,
                0.0024512597414500575,
                0.002497192516046412,
                0.0027323447989628597,
                0.0029426218174836215,
                0.0020802317241973736,
                0.0030040622360127814,
                0.002059641951585517,
                0.0024018993984688732,
                0.0023547520587111222,
                0.0023079628070049427,
                0.0027357168221736655,
                0.0023350047988488394,
                0.002818078175187111,
                0.002251088882193846,
                0.0019264763111577314,
                0.0022558188449372262,
                0.0020463057355407407,
                0.0020386274027473787,
                0.002812136013937347,
                0.0020187844577081063,
                0.002012152372695067,
                0.0025780774762525277,
                0.0018235260675496915,
                0.002053520258735208,
                0.0020812125219141736,
                0.0021073025760843475,
                0.0025206598672358428,
                0.001990464866599616,
                0.002141274796689258,
                0.002177047269309268,
                0.0020634205772212763,
                0.0019865051624091234,
                0.0022876041010022165,
                0.0030977733570205813,
                0.0019553245866999907,
                0.0022503156050601427,
                0.0019930213580236717,
                0.0022469755590838543,
                0.0018715284764766692,
                0.0023659040713134936,
                0.002573281603262705,
                0.0016922116115251008,
                0.002883965302916134,
                0.0019295286496772486,
                0.002002914490945199,
                0.0021445127258844236,
                0.0022092010387602975,
                0.00187149996704915,
                0.0018420509720111595,
                0.0021766941501375507
            ]
        },
        "start": 1701548434.3238215,
        "end": 1701548907.535534,
        "model": null
    },
    "full_log": "results_kgem\\train_2023_12_02_20_20_32.tar.gz"
}