{
    "directory_name": "train_2023_12_03_20_23_46",
    "config": {
        "dataset": "WN18-RR",
        "model": "KG2E",
        "output_dir": "/data/d1/kgem/results",
        "epochs": 1000,
        "cpu_monitor_interval": 0.5,
        "seed": 124,
        "timestamp": "2023_12_03_20_23_46"
    },
    "emissions": {
        "timestamp": {
            "0": "2023-12-03T20:26:35"
        },
        "project_name": {
            "0": "codecarbon"
        },
        "run_id": {
            "0": "9bcb61d1-2db1-4bc1-907b-b954174fff2e"
        },
        "duration": {
            "0": 167.02051854133606
        },
        "emissions": {
            "0": 0.0030152438471794
        },
        "emissions_rate": {
            "0": 1.8053134270645e-05
        },
        "cpu_power": {
            "0": 42.90523927436477
        },
        "gpu_power": {
            "0": 398.3726644277812
        },
        "ram_power": {
            "0": 23.42510032653809
        },
        "cpu_energy": {
            "0": 0.0018813080292118
        },
        "gpu_energy": {
            "0": 0.0052890514534595
        },
        "ram_energy": {
            "0": 0.0010798008480182
        },
        "energy_consumed": {
            "0": 0.0082501603306897
        },
        "country_name": {
            "0": "Germany"
        },
        "country_iso_code": {
            "0": "DEU"
        },
        "region": {
            "0": NaN
        },
        "cloud_provider": {
            "0": NaN
        },
        "cloud_region": {
            "0": NaN
        },
        "os": {
            "0": "Linux-5.15.0-88-generic-x86_64-with-glibc2.35"
        },
        "python_version": {
            "0": "3.10.12"
        },
        "codecarbon_version": {
            "0": "2.3.1"
        },
        "cpu_count": {
            "0": 32
        },
        "cpu_model": {
            "0": "13th Gen Intel(R) Core(TM) i9-13900K"
        },
        "gpu_count": {
            "0": 1
        },
        "gpu_model": {
            "0": "1 x NVIDIA GeForce RTX 4090"
        },
        "longitude": {
            "0": NaN
        },
        "latitude": {
            "0": NaN
        },
        "ram_total_size": {
            "0": 62.46693420410156
        },
        "tracking_mode": {
            "0": "machine"
        },
        "on_cloud": {
            "0": "N"
        },
        "pue": {
            "0": 1.0
        }
    },
    "execution_platform": {
        "System": "Linux",
        "Node Name": "lamws027",
        "Release": "5.15.0-88-generic",
        "Version": "#98-Ubuntu SMP Mon Oct 2 15:18:56 UTC 2023",
        "Machine": "x86_64",
        "Processor": "13th Gen Intel(R) Core(TM) i9-13900K",
        "Physical cores": 24,
        "Total cores": 32,
        "Max Frequency": 4937.5,
        "Min Frequency": 800.0,
        "Current Frequency": 3047.98609375,
        "Total": 67073359872,
        "Available": 62200471552,
        "Used": 4108828672
    },
    "results": {
        "history": {
            "loss": [
                7.251366540263681,
                3.554033397927004,
                2.4418228924274445,
                1.8040479190209333,
                1.4005657418685802,
                1.1183912485837937,
                0.9094009390648674,
                0.7418717397486463,
                0.608831809285809,
                0.5122214010533165,
                0.43785570965093723,
                0.37535060990382646,
                0.3193425620741704,
                0.2719001694198917,
                0.23361744297777906,
                0.204455801340587,
                0.18120061439626356,
                0.15934976801714476,
                0.1402720615925158,
                0.12458608692840618,
                0.11314896534690086,
                0.10188918203553733,
                0.09247963675023878,
                0.08216000571846963,
                0.0743391161894097,
                0.0689507096512791,
                0.06457292725715567,
                0.058022979931796295,
                0.055119253936059334,
                0.05233476170722176,
                0.04955945185193902,
                0.04516843499287086,
                0.043082597818883024,
                0.04144983803305556,
                0.03849685638047316,
                0.03559975855545524,
                0.03425359910025316,
                0.032047611009329555,
                0.03169691784800414,
                0.02975337746388772,
                0.028297504300580305,
                0.027406231237246708,
                0.026881653623765007,
                0.02591837699360707,
                0.02434340108952978,
                0.02325695828151177,
                0.022523655512315385,
                0.02216948306064724,
                0.02217245182460722,
                0.020387446921428336,
                0.019315154045162833,
                0.019412017558865687,
                0.01851316788507735,
                0.018040106735904428,
                0.017986928226481028,
                0.017040777726865866,
                0.016808932723806184,
                0.015757232499034966,
                0.016315659171531854,
                0.015338607417309986,
                0.015550985778955853,
                0.01565772950758829,
                0.015136359955238946,
                0.014271818975205807,
                0.013482164366937735,
                0.014181590244612272,
                0.012966371141887709,
                0.013393604432177894,
                0.012652986359727733,
                0.011904368938549476,
                0.01204630598453257,
                0.011734592802274754,
                0.011556442259975217,
                0.01160992294385591,
                0.011373458890353932,
                0.01094871552880196,
                0.010720010430497282,
                0.010783661972484825,
                0.009873298451523571,
                0.010108920553808702,
                0.010236266014330527,
                0.009580800624783425,
                0.00948413458707578,
                0.009816339601050404,
                0.009596969031126184,
                0.00958273986573605,
                0.009440995999337995,
                0.009046160070883,
                0.009069048718768445,
                0.008962522490936167,
                0.008768600117250839,
                0.008458221424371004,
                0.008431110742008861,
                0.008171783313703012,
                0.008437686583355945,
                0.008037937969407615,
                0.00851106796249309,
                0.0070711194181486085,
                0.007656139233971343,
                0.0077526162268922606,
                0.007514327835729894,
                0.008050874548087663,
                0.007476784398450571,
                0.007370712202699746,
                0.007521754847017719,
                0.007227351801360355,
                0.007049964572412564,
                0.007006573798271882,
                0.006940728710854755,
                0.007118070656981538,
                0.0068500383044866955,
                0.006532586743945585,
                0.0067899620906888124,
                0.0065843689364983755,
                0.007052139472216367,
                0.006573275684872095,
                0.006455983842384098,
                0.006477787383996388,
                0.006579615115461981,
                0.006423374970772249,
                0.006327309475882965,
                0.005817010609761757,
                0.005999896269949043,
                0.005849492736160755,
                0.0064140380908022905,
                0.005502197321723489,
                0.0060817230602397635,
                0.005644232615390245,
                0.0057365993092603545,
                0.005915218295858187,
                0.005441169077205225,
                0.005318542898577802,
                0.005685833364944248,
                0.005832804870956085,
                0.005320176810902708,
                0.005308495890623068,
                0.005206199110869099,
                0.005267640964730698,
                0.005380941483685199,
                0.005320122618885602,
                0.004825390678118257,
                0.005365972527686287,
                0.005361684882903801,
                0.005117416611927397,
                0.0051675781443276825,
                0.00489312803153606,
                0.0050684033893048765,
                0.0051920222940252106,
                0.004932895516428878,
                0.005227891170858022,
                0.005277864728122949,
                0.0047662326134741305,
                0.004617054218097645,
                0.004670829936624025,
                0.0045579837744726855,
                0.005012827547376647,
                0.004466141815132955,
                0.0049077098696109125,
                0.004575485746403608,
                0.004499797101187355,
                0.004792675644378451,
                0.004618571627446834,
                0.004583868198096752,
                0.004554946626098279,
                0.0043805336196194675,
                0.0042912172701428915,
                0.004725888985044816,
                0.004485751830917948,
                0.004294652968425961,
                0.004141120256527382,
                0.004333699489121928,
                0.004432387595229289,
                0.004113529929343392,
                0.004266355893410304,
                0.00437550383126911,
                0.003921783411437098,
                0.004314990621060133,
                0.0043376457466579536,
                0.0043844787623075875,
                0.004059161716962562,
                0.004009631966405055,
                0.0038821255952558096,
                0.0038590477560372914,
                0.003955419520464014,
                0.003962284601156545,
                0.003801337870604852,
                0.003709987474276739,
                0.003987772275200661,
                0.003979585478630136,
                0.003551452322041287,
                0.0036612208631327924,
                0.003927537436282043,
                0.0036881240249118383,
                0.0036468753372045125,
                0.003997872309649692,
                0.00366868215120014,
                0.0036880062619114623,
                0.003910057808217757,
                0.0037232164950931775,
                0.003574717724147965,
                0.003771957596216132,
                0.003822080960825962,
                0.0036335368585937162,
                0.003699913188157713,
                0.0034351796726696192,
                0.0030523233245784306,
                0.0034893463968354113,
                0.003413194774047417,
                0.0035048226873828645,
                0.0034348352743750984
            ]
        },
        "start": 1701635028.2925177,
        "end": 1701635195.3117464,
        "model": null
    },
    "full_log": "results_kgem\\train_2023_12_03_20_23_46.tar.gz"
}