{
    "directory_name": "train_2023_12_03_16_11_21",
    "config": {
        "dataset": "kinships",
        "model": "MuRE",
        "output_dir": "/data/d1/kgem/results",
        "epochs": 1000,
        "cpu_monitor_interval": 0.5,
        "seed": 124,
        "timestamp": "2023_12_03_16_11_21"
    },
    "emissions": {
        "timestamp": {
            "0": "2023-12-03T16:11:27"
        },
        "project_name": {
            "0": "codecarbon"
        },
        "run_id": {
            "0": "6ce59374-5062-4229-820f-c8e23e3e1174"
        },
        "duration": {
            "0": 4.002243757247925
        },
        "emissions": {
            "0": 5.222686740398632e-05
        },
        "emissions_rate": {
            "0": 1.304939693126019e-05
        },
        "cpu_power": {
            "0": 36.06835997745441
        },
        "gpu_power": {
            "0": 70.17538064601882
        },
        "ram_power": {
            "0": 23.42510032653809
        },
        "cpu_energy": {
            "0": 4.164719776217612e-05
        },
        "gpu_energy": {
            "0": 7.528450467475523e-05
        },
        "ram_energy": {
            "0": 2.5968856022250293e-05
        },
        "energy_consumed": {
            "0": 0.0001429005584591
        },
        "country_name": {
            "0": "Germany"
        },
        "country_iso_code": {
            "0": "DEU"
        },
        "region": {
            "0": NaN
        },
        "cloud_provider": {
            "0": NaN
        },
        "cloud_region": {
            "0": NaN
        },
        "os": {
            "0": "Linux-5.15.0-88-generic-x86_64-with-glibc2.35"
        },
        "python_version": {
            "0": "3.10.12"
        },
        "codecarbon_version": {
            "0": "2.3.1"
        },
        "cpu_count": {
            "0": 32
        },
        "cpu_model": {
            "0": "13th Gen Intel(R) Core(TM) i9-13900K"
        },
        "gpu_count": {
            "0": 1
        },
        "gpu_model": {
            "0": "1 x NVIDIA GeForce RTX 4090"
        },
        "longitude": {
            "0": NaN
        },
        "latitude": {
            "0": NaN
        },
        "ram_total_size": {
            "0": 62.46693420410156
        },
        "tracking_mode": {
            "0": "machine"
        },
        "on_cloud": {
            "0": "N"
        },
        "pue": {
            "0": 1.0
        }
    },
    "execution_platform": {
        "System": "Linux",
        "Node Name": "lamws027",
        "Release": "5.15.0-88-generic",
        "Version": "#98-Ubuntu SMP Mon Oct 2 15:18:56 UTC 2023",
        "Machine": "x86_64",
        "Processor": "13th Gen Intel(R) Core(TM) i9-13900K",
        "Physical cores": 24,
        "Total cores": 32,
        "Max Frequency": 4937.5,
        "Min Frequency": 800.0,
        "Current Frequency": 3118.8319375,
        "Total": 67073359872,
        "Available": 62232465408,
        "Used": 4076838912
    },
    "results": {
        "history": {
            "loss": [
                0.9978260503095739,
                0.9511361507808461,
                0.828084211139118,
                0.7081263871753917,
                0.5558685616535299,
                0.39705601860495177,
                0.27276172532754783,
                0.22683773145956151,
                0.20511157898341909,
                0.19297852849259095,
                0.19595497495987835,
                0.17332600758356206,
                0.17526373069952517,
                0.1690603700630805,
                0.16992218485649893,
                0.17384002620682998,
                0.1564117621849565,
                0.1569080782287261,
                0.15334498619332032,
                0.15992211594301112,
                0.15325696854030385,
                0.15466430651790955,
                0.14575181419358535,
                0.14294898225104108,
                0.15299534425139427,
                0.14902580748586094,
                0.14289512616746566,
                0.14655966180212357,
                0.14476798496702137,
                0.14124769848935745,
                0.13700475499910467,
                0.13381403355914004,
                0.138370444669443,
                0.1380997595979887,
                0.1369490811929983,
                0.13634886658366988,
                0.13459711236988797,
                0.13540562066961737,
                0.12141619819928617,
                0.13770181751426527
            ]
        },
        "start": 1701619883.209581,
        "end": 1701619887.2033782,
        "model": null
    },
    "full_log": "results_kgem\\train_2023_12_03_16_11_21.tar.gz"
}