{
    "directory_name": "train_2023_12_04_07_04_19",
    "config": {
        "dataset": "FB15k-237",
        "model": "ERMLP",
        "output_dir": "/data/d1/kgem/results",
        "epochs": 1000,
        "cpu_monitor_interval": 0.5,
        "seed": 129,
        "timestamp": "2023_12_04_07_04_19"
    },
    "emissions": {
        "timestamp": {
            "0": "2023-12-04T07:06:59"
        },
        "project_name": {
            "0": "codecarbon"
        },
        "run_id": {
            "0": "44ee3e7e-ad96-4e91-a1ea-d180ab8c0b41"
        },
        "duration": {
            "0": 159.0821921825409
        },
        "emissions": {
            "0": 0.0025728501031607
        },
        "emissions_rate": {
            "0": 1.6173086804137787e-05
        },
        "cpu_power": {
            "0": 39.68891997369733
        },
        "gpu_power": {
            "0": 222.4695797872022
        },
        "ram_power": {
            "0": 23.42510032653809
        },
        "cpu_energy": {
            "0": 0.0020093102588358
        },
        "gpu_energy": {
            "0": 0.0039991443104234
        },
        "ram_energy": {
            "0": 0.0010312499898805
        },
        "energy_consumed": {
            "0": 0.0070397045591398
        },
        "country_name": {
            "0": "Germany"
        },
        "country_iso_code": {
            "0": "DEU"
        },
        "region": {
            "0": NaN
        },
        "cloud_provider": {
            "0": NaN
        },
        "cloud_region": {
            "0": NaN
        },
        "os": {
            "0": "Linux-5.15.0-88-generic-x86_64-with-glibc2.35"
        },
        "python_version": {
            "0": "3.10.12"
        },
        "codecarbon_version": {
            "0": "2.3.1"
        },
        "cpu_count": {
            "0": 32
        },
        "cpu_model": {
            "0": "13th Gen Intel(R) Core(TM) i9-13900K"
        },
        "gpu_count": {
            "0": 1
        },
        "gpu_model": {
            "0": "1 x NVIDIA GeForce RTX 4090"
        },
        "longitude": {
            "0": NaN
        },
        "latitude": {
            "0": NaN
        },
        "ram_total_size": {
            "0": 62.46693420410156
        },
        "tracking_mode": {
            "0": "machine"
        },
        "on_cloud": {
            "0": "N"
        },
        "pue": {
            "0": 1.0
        }
    },
    "execution_platform": {
        "System": "Linux",
        "Node Name": "lamws027",
        "Release": "5.15.0-88-generic",
        "Version": "#98-Ubuntu SMP Mon Oct 2 15:18:56 UTC 2023",
        "Machine": "x86_64",
        "Processor": "13th Gen Intel(R) Core(TM) i9-13900K",
        "Physical cores": 24,
        "Total cores": 32,
        "Max Frequency": 4937.5,
        "Min Frequency": 800.0,
        "Current Frequency": 3067.722625,
        "Total": 67073359872,
        "Available": 62076628992,
        "Used": 4232687616
    },
    "results": {
        "history": {
            "loss": [
                0.6854936887605618,
                0.5229544685286166,
                0.4567716500720996,
                0.35725580193698125,
                0.26757767136267413,
                0.19336389023407607,
                0.14837368724207103,
                0.1282941497834303,
                0.12020577573036094,
                0.1125851267438841,
                0.1052511573636857,
                0.10193393107850598,
                0.10077180319158176,
                0.097484519377505,
                0.09471085177329723,
                0.09189792134407435,
                0.08970562155732599,
                0.08815190871530901,
                0.08653101717715037,
                0.08344270981785158,
                0.08196154993591674,
                0.08097867809081852,
                0.0795102426668354,
                0.07796281789931506,
                0.07523019247717265,
                0.07650489021295914,
                0.07555992109131555,
                0.07323932959518535,
                0.07210175390420999,
                0.07057142639155951,
                0.07047319420817486,
                0.07017898012166414,
                0.06879430907136241,
                0.066682095496599,
                0.06675448543668101,
                0.06456192507235962,
                0.06500216380378489,
                0.06463524160743712,
                0.06305741693172691,
                0.0638053846604218,
                0.06211789906978159,
                0.0623747564314296,
                0.060949338463801794,
                0.061330887011531825,
                0.06013363962143183,
                0.05946635607777204,
                0.059332357420781426,
                0.058887728841262164,
                0.05765122242941261,
                0.05731609033075488,
                0.05760092026644289,
                0.05640955893051226,
                0.05633016165848804,
                0.05528826563534093,
                0.05615685350916095,
                0.05519717768700277,
                0.053900851020002465,
                0.05380336818331721,
                0.0533622775957521,
                0.053440899780039394,
                0.05240161809106537,
                0.052586959020049784,
                0.05293744911903188,
                0.05153143236559035,
                0.052041501385928154,
                0.05133194935982057,
                0.05108826650089303,
                0.050742182994536485,
                0.04973102073506684,
                0.05008343788282639,
                0.04942109701263097,
                0.048792958564474576,
                0.049406707645170495,
                0.04932070750154394,
                0.04856903391766694,
                0.048245722675908036,
                0.04791685275913953,
                0.047702280649002414,
                0.04750977583520416,
                0.046991499696760974,
                0.04662765886964012,
                0.04638857064332361,
                0.04729967498547299,
                0.04655162930604235,
                0.045734884106551466,
                0.04632891592265633,
                0.04547712852896269,
                0.04519276087402751,
                0.04423262296386435,
                0.044882379585276036,
                0.04467233926537933,
                0.04532257444553799,
                0.04384171910170441,
                0.04418985930692863,
                0.0438057930495236,
                0.04336621310572409,
                0.04345726229947828,
                0.04350570029064817,
                0.04225902637748901,
                0.04293629204633585,
                0.042719303535670744,
                0.0423782987542878,
                0.043132263797344965,
                0.04120128042908317,
                0.041563723504417144,
                0.04248052396481245,
                0.042521331422486514,
                0.041491686814637226,
                0.04308198175900322,
                0.04153164617037392,
                0.040627681201644526,
                0.04093230931878594,
                0.04043540048306967,
                0.040136060479464164,
                0.04085787330768995,
                0.04036802134142798,
                0.040154349423335164,
                0.04077199156731647,
                0.03984133677551854,
                0.03856837077711132,
                0.03992761352238782,
                0.03974290360606373,
                0.03946293499898989,
                0.03912800597377395,
                0.03890604472798861,
                0.03917044494213468,
                0.039677248970690415,
                0.03818196375562563,
                0.03917067945231303,
                0.03926328785090181
            ]
        },
        "start": 1701673460.80072,
        "end": 1701673619.8809257,
        "model": null
    },
    "full_log": "results_kgem\\train_2023_12_04_07_04_19.tar.gz"
}